Stata_Table_Formatter/Format_Regression_Output.py
Stata_Table_Formatter/Reg_Obj.py
Stata_Table_Formatter/Stata_Reg_Obj.py
Stata_Table_Formatter/__init__.py
Stata_Table_Formatter/workbook.py
spyfor/Exec.py
spyfor/Format_Regression_Output.py
spyfor/Reg_Obj.py
spyfor/Stata_Reg_Obj.py
spyfor/__init__.py
spyfor/workbook.py
spyfor-0.0.5.dist-info/LICENSE
spyfor-0.0.5.dist-info/METADATA
spyfor-0.0.5.dist-info/WHEEL
spyfor-0.0.5.dist-info/top_level.txt
spyfor-0.0.5.dist-info/RECORD
