Metadata-Version: 2.1
Name: spyfor
Version: 0.0.5
Summary: Stata Regression Formatter
Home-page: https://github.com/jj48642/spyfor
Author: James J Anderson
Author-email: jj48642@gmail.com
License: MIT
Platform: UNKNOWN
Requires-Dist: pandas
Requires-Dist: xlsxwriter
Requires-Dist: numpy
